blinky.v
module SOC (
    input CLK,
    input RESET,
    output [1:0] LEDS,
    input RXD,
    output TXD

);

  reg [3:0] clk_divider = 0;  // 8-bit counter for clock divider 
  reg slow_clk = 0;  // Keeps track if the slow clock is high or low

  always @(negedge CLK) begin
    clk_divider <= clk_divider + 1;
    if (clk_divider == 3'd0) begin  // when overflowing to 0 at 7bit reg
      slow_clk <= ~slow_clk;  // negate the slow clk (from low to high or vice versa)
    end
  end

  reg [1:0] count = 0; // this is still the same led counter thingy, but now use the internal slower clock instead
  always @(negedge slow_clk) begin
    count <= count + 1;
  end


  assign LEDS = count;
  assign TXD  = 1'b0;  // not used for now

endmodule

testbench.v
module bench ();
  reg CLK;
  wire RESET = 0;
  wire [1:0] LEDS;
  reg RXD = 1'b0;
  wire TXD;

  SOC uut (
      .CLK  (CLK),
      .RESET(RESET),
      .LEDS (LEDS),
      .RXD  (RXD),
      .TXD  (TXD)
  );

  reg [1:0] prev_LEDS = 0;

  initial begin
    $dumpfile("soc_testbench.vcd");
    $dumpvars(0, bench);
  end

  initial begin
    CLK = 0;
    forever begin
      #1 CLK = ~CLK;
      if (LEDS != prev_LEDS) begin
        $display("LEDS = %b", LEDS);
      end
      prev_LEDS <= LEDS;
    end
  end
endmodule

soc_testbench.vcd
$date
	Sat Aug  2 15:29:46 2025
$end
$version
	Icarus Verilog
$end
$timescale
	1s
$end
$scope module bench $end
$var wire 1 ! RESET $end
$var wire 1 " TXD $end
$var wire 2 # LEDS [1:0] $end
$var reg 1 $ CLK $end
$var reg 1 % RXD $end
$var reg 2 & prev_LEDS [1:0] $end
$scope module uut $end
$var wire 1 $ CLK $end
$var wire 2 ' LEDS [1:0] $end
$var wire 1 ! RESET $end
$var wire 1 % RXD $end
$var wire 1 " TXD $end
$var reg 4 ( clk_divider [3:0] $end
$var reg 2 ) count [1:0] $end
$var reg 1 * slow_clk $end
$upscope $end
$upscope $end
$enddefinitions $end
$comment Show the parameter values. $end
$dumpall
$end
#0
$dumpvars
1*
b0 )
b1 (
b0 '
b0 &
0%
0$
b0 #
0"
0!
$end
#1
1$
#2
b10 (
0$
#3
1$
#4
b11 (
0$
#5
1$
#6
b100 (
0$
#7
1$
#8
b101 (
0$
#9
1$
#10
b110 (
0$
#11
1$
#12
b111 (
0$
#13
1$
#14
b1000 (
0$
#15
1$
#16
b1001 (
0$
#17
1$
#18
b1010 (
0$
#19
1$
#20
b1011 (
0$
#21
1$
#22
b1100 (
0$
#23
1$
#24
b1101 (
0$
#25
1$
#26
b1110 (
0$
#27
1$
#28
b1111 (
0$
#29
1$
#30
b0 (
0$
#31
1$
#32
b1 #
b1 '
b1 )
0*
b1 (
0$
#33
b1 &
1$
#34
b10 (
0$
#35
1$
#36
b11 (
0$
#37
1$
#38
b100 (
0$
#39
1$
#40
b101 (
0$
#41
1$
#42
b110 (
0$
#43
1$
#44
b111 (
0$
#45
1$
#46
b1000 (
0$
#47
1$
#48
b1001 (
0$
#49
1$
#50
b1010 (
0$
#51
1$
#52
b1011 (
0$
#53
1$
#54
b1100 (
0$
#55
1$
#56
b1101 (
0$
#57
1$
#58
b1110 (
0$
#59
1$
#60
b1111 (
0$
#61
1$
#62
b0 (
0$
#63
1$
#64
1*
b1 (
0$
#65
1$
#66
b10 (
0$
#67
1$
#68
b11 (
0$
#69
1$
#70
b100 (
0$
#71
1$
#72
b101 (
0$
#73
1$
#74
b110 (
0$
#75
1$
#76
b111 (
0$
#77
1$
#78
b1000 (
0$
#79
1$
#80
b1001 (
0$
#81
1$
#82
b1010 (
0$
#83
1$
#84
b1011 (
0$
#85
1$
#86
b1100 (
0$
#87
1$
#88
b1101 (
0$
#89
1$
#90
b1110 (
0$
#91
1$
#92
b1111 (
0$
#93
1$
#94
b0 (
0$
#95
1$
#96
b10 #
b10 '
b10 )
0*
b1 (
0$
#97
b10 &
1$
#98
b10 (
0$
#99
1$
#100
b11 (
0$
#101
1$
#102
b100 (
0$
#103
1$
#104
b101 (
0$
#105
1$
#106
b110 (
0$
#107
1$
#108
b111 (
0$
#109
1$
#110
b1000 (
0$
#111
1$
#112
b1001 (
0$
#113
1$
#114
b1010 (
0$
#115
1$
#116
b1011 (
0$
#117
1$
#118
b1100 (
0$
#119
1$
#120
b1101 (
0$
#121
1$
#122
b1110 (
0$
#123
1$
#124
b1111 (
0$
#125
1$
#126
b0 (
0$
#127
1$
#128
1*
b1 (
0$
#129
1$
#130
b10 (
0$
#131
1$
#132
b11 (
0$
#133
1$
#134
b100 (
0$
#135
1$
#136
b101 (
0$
#137
1$
#138
b110 (
0$
#139
1$
#140
b111 (
0$
#141
1$
#142
b1000 (
0$
#143
1$
#144
b1001 (
0$
#145
1$
#146
b1010 (
0$
#147
1$
#148
b1011 (
0$
#149
1$
#150
b1100 (
0$
#151
1$
#152
b1101 (
0$
#153
1$
#154
b1110 (
0$
#155
1$
#156
b1111 (
0$
#157
1$
#158
b0 (
0$
#159
1$
#160
b11 #
b11 '
b11 )
0*
b1 (
0$
#161
b11 &
1$
#162
b10 (
0$
#163
1$
#164
b11 (
0$
#165
1$
#166
b100 (
0$
#167
1$
#168
b101 (
0$
#169
1$
#170
b110 (
0$
#171
1$
#172
b111 (
0$
#173
1$
#174
b1000 (
0$
#175
1$
#176
b1001 (
0$
#177
1$
#178
b1010 (
0$
#179
1$
#180
b1011 (
0$
#181
1$
#182
b1100 (
0$
#183
1$
#184
b1101 (
0$
#185
1$
#186
b1110 (
0$
#187
1$
#188
b1111 (
0$
#189
1$
#190
b0 (
0$
#191
1$
#192
1*
b1 (
0$
#193
1$
#194
b10 (
0$
#195
1$
#196
b11 (
0$
#197
1$
#198
b100 (
0$
#199
1$
#200
b101 (
0$
#201
1$
#202
b110 (
0$
#203
1$
#204
b111 (
0$
#205
1$
#206
b1000 (
0$
#207
1$
#208
b1001 (
0$
#209
1$
#210
b1010 (
0$
#211
1$
#212
b1011 (
0$
#213
1$
#214
b1100 (
0$
#215
1$
#216
b1101 (
0$
#217
1$
#218
b1110 (
0$
#219
1$
#220
b1111 (
0$
#221
1$
#222
b0 (
0$
#223
1$
#224
b0 #
b0 '
b0 )
0*
b1 (
0$
#225
b0 &
1$
#226
b10 (
0$
#227
1$
#228
b11 (
0$
#229
1$
#230
b100 (
0$
#231
1$
#232
b101 (
0$
#233
1$
#234
b110 (
0$
#235
1$
#236
b111 (
0$
#237
1$
#238
b1000 (
0$
#239
1$
#240
b1001 (
0$
#241
1$
#242
b1010 (
0$
#243
1$
#244
b1011 (
0$
#245
1$
#246
b1100 (
0$
#247
1$
#248
b1101 (
0$
#249
1$
#250
b1110 (
0$
#251
1$
#252
b1111 (
0$
#253
1$
#254
b0 (
0$
#255
1$
#256
1*
b1 (
0$
#257
1$
#258
b10 (
0$
#259
1$
#260
b11 (
0$
#261
1$
#262
b100 (
0$
#263
1$
#264
b101 (
0$
#265
1$
#266
b110 (
0$
#267
1$
#268
b111 (
0$
#269
1$
#270
b1000 (
0$
#271
1$
#272
b1001 (
0$
#273
1$
#274
b1010 (
0$
#275
1$
#276
b1011 (
0$
#277
1$
#278
b1100 (
0$
#279
1$
#280
b1101 (
0$
#281
1$
#282
b1110 (
0$
#283
1$
#284
b1111 (
0$
#285
1$
#286
b0 (
0$
#287
1$
#288
b1 #
b1 '
b1 )
0*
b1 (
0$
#289
b1 &
1$
#290
b10 (
0$
#291
1$
#292
b11 (
0$
#293
1$
#294
b100 (
0$
#295
1$
#296
b101 (
0$
#297
1$
#298
b110 (
0$
#299
1$
#300
b111 (
0$
#301
1$
#302
b1000 (
0$
#303
1$
#304
b1001 (
0$
#305
1$
#306
b1010 (
0$
#307
1$
#308
b1011 (
0$
#309
1$
#310
b1100 (
0$
#311
1$
#312
b1101 (
0$
#313
1$
#314
b1110 (
0$
#315
1$
#316
b1111 (
0$
#317
1$
#318
b0 (
0$
#319
1$
#320
1*
b1 (
0$
#321
1$
#322
b10 (
0$
#323
1$
#324
b11 (
0$
#325
1$
#326
b100 (
0$
#327
1$
#328
b101 (
0$
#329
1$
#330
b110 (
0$
#331
1$
#332
b111 (
0$
#333
1$
#334
b1000 (
0$
#335
1$
#336
b1001 (
0$
#337
1$
#338
b1010 (
0$
#339
1$
#340
b1011 (
0$
#341
1$
#342
b1100 (
0$
#343
1$
#344
b1101 (
0$
#345
1$
#346
b1110 (
0$
#347
1$
#348
b1111 (
0$
#349
1$
#350
b0 (
0$
#351
1$
#352
b10 #
b10 '
b10 )
0*
b1 (
0$
#353
b10 &
1$
#354
b10 (
0$
#355
1$
#356
b11 (
0$
#357
1$
#358
b100 (
0$
#359
1$
#360
b101 (
0$
#361
1$
#362
b110 (
0$
#363
1$
#364
b111 (
0$
#365
1$
#366
b1000 (
0$
#367
1$
#368
b1001 (
0$
#369
1$
#370
b1010 (
0$
#371
1$
#372
b1011 (
0$
#373
1$
#374
b1100 (
0$
#375
1$
#376
b1101 (
0$
#377
1$
#378
b1110 (
0$
#379
1$
#380
b1111 (
0$
#381
1$
#382
b0 (
0$
#383
1$
#384
1*
b1 (
0$
#385
1$
#386
b10 (
0$
#387
1$
#388
b11 (
0$
#389
1$
#390
b100 (
0$
#391
1$
#392
b101 (
0$
#393
1$
#394
b110 (
0$
#395
1$
#396
b111 (
0$
#397
1$
#398
b1000 (
0$
#399
1$
#400
b1001 (
0$
#401
1$
#402
b1010 (
0$
#403
1$
#404
b1011 (
0$
#405
1$
#406
b1100 (
0$
#407
1$
#408
b1101 (
0$
#409
1$
#410
b1110 (
0$
#411
1$
#412
b1111 (
0$
#413
1$
#414
b0 (
0$
#415
1$
#416
b11 #
b11 '
b11 )
0*
b1 (
0$
#417
b11 &
1$
#418
b10 (
0$
#419
1$
#420
b11 (
0$
#421
1$
#422
b100 (
0$
#423
1$
#424
b101 (
0$
#425
1$
#426
b110 (
0$
#427
1$
#428
b111 (
0$
#429
1$
#430
b1000 (
0$
#431
1$
#432
b1001 (
0$
#433
1$
#434
b1010 (
0$
#435
1$
#436
b1011 (
0$
#437
1$
#438
b1100 (
0$
#439
1$
#440
b1101 (
0$
#441
1$
#442
b1110 (
0$
#443
1$
#444
b1111 (
0$
#445
1$
#446
b0 (
0$
#447
1$
#448
1*
b1 (
0$
#449
1$
#450
b10 (
0$
#451
1$
#452
b11 (
0$
#453
1$
#454
b100 (
0$
#455
1$
#456
b101 (
0$
#457
1$
#458
b110 (
0$
#459
1$
#460
b111 (
0$
#461
1$
#462
b1000 (
0$
#463
1$
#464
b1001 (
0$
#465
1$
#466
b1010 (
0$
#467
1$
#468
b1011 (
0$
#469
1$
#470
b1100 (
0$
#471
1$
#472
b1101 (
0$
#473
1$
#474
b1110 (
0$
#475
1$
#476
b1111 (
0$
#477
1$
#478
b0 (
0$
#479
1$
#480
b0 #
b0 '
b0 )
0*
b1 (
0$
#481
b0 &
1$
#482
b10 (
0$
#483
1$
#484
b11 (
0$
#485
1$
#486
b100 (
0$
#487
1$
#488
b101 (
0$
#489
1$
#490
b110 (
0$
#491
1$
#492
b111 (
0$
#493
1$
#494
b1000 (
0$
#495
1$
#496
b1001 (
0$
#497
1$
#498
b1010 (
0$
#499
1$
#500
b1011 (
0$
#501
1$
#502
b1100 (
0$
#503
1$
#504
b1101 (
0$
#505
1$
#506
b1110 (
0$
#507
1$
#508
b1111 (
0$
#509
1$
#510
b0 (
0$
#511
1$
#512
1*
b1 (
0$
#513
1$
#514
b10 (
0$
#515
1$
#516
b11 (
0$
#517
1$
#518
b100 (
0$
#519
1$
#520
b101 (
0$
#521
1$
#522
b110 (
0$
#523
1$
#524
b111 (
0$
#525
1$
#526
b1000 (
0$
#527
1$
#528
b1001 (
0$
#529
1$
#530
b1010 (
0$
#531
1$
#532
b1011 (
0$
#533
1$
#534
b1100 (
0$
#535
1$
#536
b1101 (
0$
#537
1$
#538
b1110 (
0$
#539
1$
#540
b1111 (
0$
#541
1$
#542
b0 (
0$
#543
1$
#544
b1 #
b1 '
b1 )
0*
b1 (
0$
#545
b1 &
1$
#546
b10 (
0$
#547
1$
#548
b11 (
0$
#549
1$
#550
b100 (
0$
#551
1$
#552
b101 (
0$
#553
1$
#554
b110 (
0$
#555
1$
#556
b111 (
0$
#557
1$
#558
b1000 (
0$
#559
1$
#560
b1001 (
0$
#561
1$
#562
b1010 (
0$
#563
1$
#564
b1011 (
0$
#565
1$
#566
b1100 (
0$
#567
1$
#568
b1101 (
0$
#569
1$
#570
b1110 (
0$
#571
1$
#572
b1111 (
0$
#573
1$
#574
b0 (
0$
#575
1$
#576
1*
b1 (
0$
#577
1$
#578
b10 (
0$
#579
1$
#580
b11 (
0$
#581
1$
#582
b100 (
0$
#583
1$
#584
b101 (
0$
#585
1$
#586
b110 (
0$
#587
1$
#588
b111 (
0$
#589
1$
#590
b1000 (
0$
#591
1$
#592
b1001 (
0$
#593
1$
#594
b1010 (
0$
#595
1$
#596
b1011 (
0$
#597
1$
#598
b1100 (
0$
#599
1$
#600
b1101 (
0$
#601
1$
#602
b1110 (
0$
#603
1$
#604
b1111 (
0$
#605
1$
#606
b0 (
0$
#607
1$
#608
b10 #
b10 '
b10 )
0*
b1 (
0$
#609
b10 &
1$
#610
b10 (
0$
#611
1$
#612
b11 (
0$
#613
1$
#614
b100 (
0$
#615
1$
#616
b101 (
0$
#617
1$
#618
b110 (
0$
#619
1$
#620
b111 (
0$
#621
1$
#622
b1000 (
0$
#623
1$
#624
b1001 (
0$
#625
1$
#626
b1010 (
0$
#627
1$
#628
b1011 (
0$
#629
1$
#630
b1100 (
0$
#631
1$
#632
b1101 (
0$
#633
1$
#634
b1110 (
0$
#635
1$
#636
b1111 (
0$
#637
1$
#638
b0 (
0$
#639
1$
#640
1*
b1 (
0$
#641
1$
#642
b10 (
0$
#643
1$
#644
b11 (
0$
#645
1$
#646
b100 (
0$
#647
1$
#648
b101 (
0$
#649
1$
#650
b110 (
0$
#651
1$
#652
b111 (
0$
#653
1$
#654
b1000 (
0$
#655
1$
#656
b1001 (
0$
#657
1$
#658
b1010 (
0$
#659
1$
#660
b1011 (
0$
#661
1$
#662
b1100 (
0$
#663
1$
#664
b1101 (
0$
#665
1$
#666
b1110 (
0$
#667
1$
#668
b1111 (
0$
#669
1$
#670
b0 (
0$
#671
1$
#672
b11 #
b11 '
b11 )
0*
b1 (
0$
#673
b11 &
1$
#674
b10 (
0$
#675
1$
#676
b11 (
0$
#677
1$
#678
b100 (
0$
#679
1$
#680
b101 (
0$
#681
1$
#682
b110 (
0$
#683
1$
#684
b111 (
0$
#685
1$
#686
b1000 (
0$
#687
1$
#688
b1001 (
0$
#689
1$
#690
b1010 (
0$
#691
1$
#692
b1011 (
0$
#693
1$
#694
b1100 (
0$
#695
1$
#696
b1101 (
0$
#697
1$
#698
b1110 (
0$
#699
1$
#700
b1111 (
0$
#701
1$
#702
b0 (
0$
#703
1$
#704
1*
b1 (
0$
#705
1$
#706
b10 (
0$
#707
1$
#708
b11 (
0$
#709
1$
#710
b100 (
0$
#711
1$
#712
b101 (
0$
#713
1$
#714
b110 (
0$
#715
1$
#716
b111 (
0$
#717
1$
#718
b1000 (
0$
#719
1$
#720
b1001 (
0$
#721
1$
#722
b1010 (
0$
#723
1$
#724
b1011 (
0$
#725
1$
#726
b1100 (
0$
#727
1$
#728
b1101 (
0$
#729
1$
#730
b1110 (
0$
#731
1$
#732
b1111 (
0$
#733
1$
#734
b0 (
0$
#735
1$
#736
b0 #
b0 '
b0 )
0*
b1 (
0$
#737
b0 &
1$
#738
b10 (
0$
#739
1$
#740
b11 (
0$
#741
1$
#742
b100 (
0$
#743
1$
#744
b101 (
0$
#745
1$
#746
b110 (
0$
#747
1$
#748
b111 (
0$
#749
1$
#750
b1000 (
0$
#751
1$
#752
b1001 (
0$
#753
1$
#754
b1010 (
0$
#755
1$
#756
b1011 (
0$
#757
1$
#758
b1100 (
0$
#759
1$
#760
b1101 (
0$
#761
1$
#762
b1110 (
0$
#763
1$
#764
b1111 (
0$
#765
1$
#766
b0 (
0$
#767
1$
#768
1*
b1 (
0$
#769
1$
#770
b10 (
0$
#771
1$
#772
b11 (
0$
#773
1$
#774
b100 (
0$
#775
1$
#776
b101 (
0$
#777
1$
#778
b110 (
0$
#779
1$
#780
b111 (
0$
#781
1$
#782
b1000 (
0$
#783
1$
#784
b1001 (
0$
#785
1$
#786
b1010 (
0$
#787
1$
#788
b1011 (
0$
#789
1$
#790
b1100 (
0$
#791
1$
#792
b1101 (
0$
#793
1$
#794
b1110 (
0$
#795
1$
#796
b1111 (
0$
#797
1$
#798
b0 (
0$
#799
1$
#800
b1 #
b1 '
b1 )
0*
b1 (
0$
#801
b1 &
1$
#802
b10 (
0$
#803
1$
#804
b11 (
0$
#805
1$
#806
b100 (
0$
#807
1$
#808
b101 (
0$
#809
1$
#810
b110 (
0$
#811
1$
#812
b111 (
0$
#813
1$
#814
b1000 (
0$
#815
1$
#816
b1001 (
0$
#817
1$
#818
b1010 (
0$
#819
1$
#820
b1011 (
0$
#821
1$
#822
b1100 (
0$
#823
1$
#824
b1101 (
0$
#825
1$
#826
b1110 (
0$
#827
1$
#828
b1111 (
0$
#829
1$
#830
b0 (
0$
#831
1$
#832
1*
b1 (
0$
#833
1$
#834
b10 (
0$
#835
1$
#836
b11 (
0$
#837
1$
#838
b100 (
0$
#839
1$
#840
b101 (
0$
#841
1$
#842
b110 (
0$
#843
1$
#844
b111 (
0$
#845
1$
#846
b1000 (
0$
#847
1$
#848
b1001 (
0$
#849
1$
#850
b1010 (
0$
#851
1$
#852
b1011 (
0$
#853
1$
#854
b1100 (
0$
#855
1$
#856
b1101 (
0$
#857
1$
#858
b1110 (
0$
#859
1$
#860
b1111 (
0$
#861
1$
#862
b0 (
0$
#863
1$
#864
b10 #
b10 '
b10 )
0*
b1 (
0$
#865
b10 &
1$
#866
b10 (
0$
#867
1$
#868
b11 (
0$
#869
1$
#870
b100 (
0$
#871
1$
#872
b101 (
0$
#873
1$
#874
b110 (
0$
#875
1$
#876
b111 (
0$
#877
1$
#878
b1000 (
0$
#879
1$
#880
b1001 (
0$
#881
1$
#882
b1010 (
0$
#883
1$
#884
b1011 (
0$
#885
1$
#886
b1100 (
0$
#887
1$
#888
b1101 (
0$
#889
1$
#890
b1110 (
0$
#891
1$
#892
b1111 (
0$
#893
1$
#894
b0 (
0$
#895
1$
#896
1*
b1 (
0$
#897
1$
#898
b10 (
0$
#899
1$
#900
b11 (
0$
#901
1$
#902
b100 (
0$
#903
1$
#904
b101 (
0$
#905
1$
#906
b110 (
0$
#907
1$
#908
b111 (
0$
#909
1$
#910
b1000 (
0$
#911
1$
#912
b1001 (
0$
#913
1$
#914
b1010 (
0$
#915
1$
#916
b1011 (
0$
#917
1$
#918
b1100 (
0$
#919
1$
#920
b1101 (
0$
#921
1$
#922
b1110 (
0$
#923
1$
#924
b1111 (
0$
#925
1$
#926
b0 (
0$
#927
1$
#928
b11 #
b11 '
b11 )
0*
b1 (
0$
#929
b11 &
1$
#930
b10 (
0$
#931
1$
#932
b11 (
0$
#933
1$
#934
b100 (
0$
#935
1$
#936
b101 (
0$
#937
1$
#938
b110 (
0$
#939
1$
#940
b111 (
0$
#941
1$
#942
b1000 (
0$
#943
1$
#944
b1001 (
0$
#945
1$
#946
b1010 (
0$
#947
1$
#948
b1011 (
0$
#949
1$
#950
b1100 (
0$
#951
1$
#952
b1101 (
0$
#953
1$
#954
b1110 (
0$
#955
1$
#956
b1111 (
0$
#957
1$
#958
b0 (
0$
#959
1$
#960
1*
b1 (
0$
#961
1$
#962
b10 (
0$
#963
1$
#964
b11 (
0$
#965
1$
#966
b100 (
0$
#967
1$
#968
b101 (
0$
#969
1$
#970
b110 (
0$
#971
1$
#972
b111 (
0$
#973
1$
#974
b1000 (
0$
#975
1$
#976
b1001 (
0$
#977
1$
#978
b1010 (
0$
#979
1$
#980
b1011 (
0$
#981
1$
#982
b1100 (
0$
#983
1$
#984
b1101 (
0$
#985
1$
#986
b1110 (
0$
#987
1$
#988
b1111 (
0$
#989
1$
#990
b0 (
0$
#991
1$
#992
b0 #
b0 '
b0 )
0*
b1 (
0$
#993
b0 &
1$
#994
b10 (
0$
#995
1$
#996
b11 (
0$
#997
1$
#998
b100 (
0$
#999
1$
#1000
b101 (
0$
#1001
1$
#1002
b110 (
0$
#1003
1$
#1004
b111 (
0$
#1005
1$
#1006
b1000 (
0$
#1007
1$
#1008
b1001 (
0$
#1009
1$
#1010
b1010 (
0$
#1011
1$
#1012
b1011 (
0$
#1013
1$
#1014
b1100 (
0$
#1015
1$
#1016
b1101 (
0$
#1017
1$
#1018
b1110 (
0$
#1019
1$
#1020
b1111 (
0$
#1021
1$
#1022
b0 (
0$
#1023
1$
#1024
1*
b1 (
0$
#1025
1$
#1026
b10 (
0$
#1027
1$
#1028
b11 (
0$
#1029
1$
#1030
b100 (
0$
#1031
1$
#1032
b101 (
0$
#1033
1$
#1034
b110 (
0$
#1035
1$
#1036
b111 (
0$
#1037
1$
#1038
b1000 (
0$
#1039
1$
#1040
b1001 (
0$
#1041
1$
#1042
b1010 (
0$
#1043
1$
#1044
b1011 (
0$
#1045
1$
#1046
b1100 (
0$
#1047
1$
#1048
b1101 (
0$
#1049
1$
#1050
b1110 (
0$
#1051
1$
#1052
b1111 (
0$
#1053
1$
#1054
b0 (
0$
#1055
1$
#1056
b1 #
b1 '
b1 )
0*
b1 (
0$
#1057
b1 &
1$
#1058
b10 (
0$
#1059
1$
#1060
b11 (
0$
#1061
1$
#1062
b100 (
0$
#1063
1$
#1064
b101 (
0$
#1065
1$
#1066
b110 (
0$
#1067
1$
#1068
b111 (
0$
#1069
1$
#1070
b1000 (
0$
#1071
1$
#1072
b1001 (
0$
#1073
1$
#1074
b1010 (
0$
#1075
1$
#1076
b1011 (
0$
#1077
1$
#1078
b1100 (
0$
#1079
1$
#1080
b1101 (
0$
#1081
1$
#1082
b1110 (
0$
#1083
1$
#1084
b1111 (
0$
#1085
1$
#1086
b0 (
0$
#1087
1$
#1088
1*
b1 (
0$
#1089
1$
#1090
b10 (
0$
#1091
1$
#1092
b11 (
0$
#1093
1$
#1094
b100 (
0$
#1095
1$
#1096
b101 (
0$
#1097
1$
#1098
b110 (
0$
#1099
1$
#1100
b111 (
0$
#1101
1$
#1102
b1000 (
0$
#1103
1$
#1104
b1001 (
0$
#1105
1$
#1106
b1010 (
0$
#1107
1$
#1108
b1011 (
0$
#1109
1$
#1110
b1100 (
0$
#1111
1$
#1112
b1101 (
0$
#1113
1$
#1114
b1110 (
0$
#1115
1$
#1116
b1111 (
0$
#1117
1$
#1118
b0 (
0$
#1119
1$
#1120
b10 #
b10 '
b10 )
0*
b1 (
0$
#1121
b10 &
1$
#1122
b10 (
0$
#1123
1$
#1124
b11 (
0$
#1125
1$
#1126
b100 (
0$
#1127
1$
#1128
b101 (
0$
#1129
1$
#1130
b110 (
0$
#1131
1$
#1132
b111 (
0$
#1133
1$
#1134
b1000 (
0$
#1135
1$
#1136
b1001 (
0$
#1137
1$
#1138
b1010 (
0$
#1139
1$
#1140
b1011 (
0$
#1141
1$
#1142
b1100 (
0$
#1143
1$
#1144
b1101 (
0$
#1145
1$
#1146
b1110 (
0$
#1147
1$
#1148
b1111 (
0$
#1149
1$
#1150
b0 (
0$
#1151
1$
#1152
1*
b1 (
0$
#1153
1$
#1154
b10 (
0$
#1155
1$
#1156
b11 (
0$
#1157
1$
#1158
b100 (
0$
#1159
1$
#1160
b101 (
0$
#1161
1$
#1162
b110 (
0$
#1163
1$
#1164
b111 (
0$
#1165
1$
#1166
b1000 (
0$
#1167
1$
#1168
b1001 (
0$
#1169
1$
#1170
b1010 (
0$
#1171
1$
#1172
b1011 (
0$
#1173
1$
#1174
b1100 (
0$
#1175
1$
#1176
b1101 (
0$
#1177
1$
#1178
b1110 (
0$
#1179
1$
#1180
b1111 (
0$
#1181
1$
#1182
b0 (
0$
#1183
1$
#1184
b11 #
b11 '
b11 )
0*
b1 (
0$
#1185
b11 &
1$
#1186
b10 (
0$
#1187
1$
#1188
b11 (
0$
#1189
1$
#1190
b100 (
0$
#1191
1$
#1192
b101 (
0$
#1193
1$
#1194
b110 (
0$
#1195
1$
#1196
b111 (
0$
#1197
1$
#1198
b1000 (
0$
#1199
1$
#1200
b1001 (
0$
#1201
1$
#1202
b1010 (
0$
#1203
1$
#1204
b1011 (
0$
#1205
1$
#1206
b1100 (
0$
#1207
1$
#1208
b1101 (
0$
#1209
1$
#1210
b1110 (
0$
#1211
1$
#1212
b1111 (
0$
#1213
1$
#1214
b0 (
0$
#1215
1$
#1216
1*
b1 (
0$
#1217
1$
#1218
b10 (
0$
#1219
1$
#1220
b11 (
0$
#1221
1$
#1222
b100 (
0$
#1223
1$
#1224
b101 (
0$
#1225
1$
#1226
b110 (
0$
#1227
1$
#1228
b111 (
0$
#1229
1$
#1230
b1000 (
0$
#1231
1$
#1232
b1001 (
0$
#1233
1$
#1234
b1010 (
0$
#1235
1$
#1236
b1011 (
0$
#1237
1$
#1238
b1100 (
0$
#1239
1$
#1240
b1101 (
0$
#1241
1$
#1242
b1110 (
0$
#1243
1$
#1244
b1111 (
0$
#1245
1$
#1246
b0 (
0$
#1247
1$
#1248
b0 #
b0 '
b0 )
0*
b1 (
0$
#1249
b0 &
1$
#1250
b10 (
0$
#1251
1$
#1252
b11 (
0$
#1253
1$
#1254
b100 (
0$
#1255
1$
#1256
b101 (
0$
#1257
1$
#1258
b110 (
0$
#1259
1$
#1260
b111 (
0$
#1261
1$
#1262
b1000 (
0$
#1263
1$
#1264
b1001 (
0$
#1265
1$
#1266
b1010 (
0$
#1267
1$
#1268
b1011 (
0$
#1269
1$
#1270
b1100 (
0$
#1271
1$
#1272
b1101 (
0$
#1273
1$
#1274
b1110 (
0$
#1275
1$
#1276
b1111 (
0$
#1277
1$
#1278
b0 (
0$
#1279
1$
#1280
1*
b1 (
0$
#1281
1$
#1282
b10 (
0$
#1283
1$
#1284
b11 (
0$
#1285
1$
#1286
b100 (
0$
#1287
1$
#1288
b101 (
0$
#1289
1$
#1290
b110 (
0$
#1291
1$
#1292
b111 (
0$
#1293
1$
#1294
b1000 (
0$
#1295
1$
#1296
b1001 (
0$
#1297
1$
#1298
b1010 (
0$
#1299
1$
#1300
b1011 (
0$
#1301
1$
#1302
b1100 (
0$
#1303
1$
#1304
b1101 (
0$
#1305
1$
#1306
b1110 (
0$
#1307
1$
#1308
b1111 (
0$
#1309
1$
#1310
b0 (
0$
#1311
1$
#1312
b1 #
b1 '
b1 )
0*
b1 (
0$
#1313
b1 &
1$
#1314
b10 (
0$
#1315
1$
#1316
b11 (
0$
#1317
1$
#1318
b100 (
0$
#1319
1$
#1320
b101 (
0$
#1321
1$
#1322
b110 (
0$
#1323
1$
#1324
b111 (
0$
#1325
1$
#1326
b1000 (
0$
#1327
1$
#1328
b1001 (
0$
#1329
1$
#1330
b1010 (
0$
#1331
1$
#1332
b1011 (
0$
#1333
1$
#1334
b1100 (
0$
#1335
1$
#1336
b1101 (
0$
#1337
1$
#1338
b1110 (
0$
#1339
1$
#1340
b1111 (
0$
#1341
1$
#1342
b0 (
0$
#1343
1$
#1344
1*
b1 (
0$
#1345
1$
#1346
b10 (
0$
#1347
1$
#1348
b11 (
0$
#1349
1$
#1350
b100 (
0$
#1351
1$
#1352
b101 (
0$
#1353
1$
#1354
b110 (
0$
#1355
1$
#1356
b111 (
0$
#1357
1$
#1358
b1000 (
0$
#1359
1$
#1360
b1001 (
0$
#1361
1$
#1362
b1010 (
0$
#1363
1$
#1364
b1011 (
0$
#1365
1$
#1366
b1100 (
0$
#1367
1$
#1368
b1101 (
0$
#1369
1$
#1370
b1110 (
0$
#1371
1$
#1372
b1111 (
0$
#1373
1$
#1374
b0 (
0$
#1375
1$
#1376
b10 #
b10 '
b10 )
0*
b1 (
0$
#1377
b10 &
1$
#1378
b10 (
0$
#1379
1$
#1380
b11 (
0$
#1381
1$
#1382
b100 (
0$
#1383
1$
#1384
b101 (
0$
#1385
1$
#1386
b110 (
0$
#1387
1$
#1388
b111 (
0$
#1389
1$
#1390
b1000 (
0$
#1391
1$
#1392
b1001 (
0$
#1393
1$
#1394
b1010 (
0$
#1395
1$
#1396
b1011 (
0$
#1397
1$
#1398
b1100 (
0$
#1399
1$
#1400
b1101 (
0$
#1401
1$
#1402
b1110 (
0$
#1403
1$
#1404
b1111 (
0$
#1405
1$
#1406
b0 (
0$
#1407
1$
#1408
1*
b1 (
0$
#1409
1$
#1410
b10 (
0$
#1411
1$
#1412
b11 (
0$
#1413
1$
#1414
b100 (
0$
#1415
1$
#1416
b101 (
0$
#1417
1$
#1418
b110 (
0$
#1419
1$
#1420
b111 (
0$
#1421
1$
#1422
b1000 (
0$
#1423
1$
#1424
b1001 (
0$
#1425
1$
#1426
b1010 (
0$
#1427
1$
#1428
b1011 (
0$
#1429
1$
#1430
b1100 (
0$
#1431
1$
#1432
b1101 (
0$
#1433
1$
#1434
b1110 (
0$
#1435
1$
#1436
b1111 (
0$
#1437
1$
#1438
b0 (
0$
#1439
1$
#1440
b11 #
b11 '
b11 )
0*
b1 (
0$
#1441
b11 &
1$
#1442
b10 (
0$
#1443
1$
#1444
b11 (
0$
#1445
1$
#1446
b100 (
0$
#1447
1$
#1448
b101 (
0$
#1449
1$
#1450
b110 (
0$
#1451
1$
#1452
b111 (
0$
#1453
1$
#1454
b1000 (
0$
#1455
1$
#1456
b1001 (
0$
#1457
1$
#1458
b1010 (
0$
#1459
1$
#1460
b1011 (
0$
#1461
1$
#1462
b1100 (
0$
#1463
1$
#1464
b1101 (
0$
#1465
1$
#1466
b1110 (
0$
#1467
1$
#1468
b1111 (
0$
#1469
1$
#1470
b0 (
0$
#1471
1$
